README.md
setup.py
ford_prefect.egg-info/PKG-INFO
ford_prefect.egg-info/SOURCES.txt
ford_prefect.egg-info/dependency_links.txt
ford_prefect.egg-info/requires.txt
ford_prefect.egg-info/top_level.txt
prefect/__init__.py